flask_datatables/__init__.py
flask_datatables/app.py
flask_datatables/database.py
flask_datatables/fields.py
flask_datatables/model.py
flask_datatables/py.typed
flask_datatables/typing.py
flask_datatables/utils.py
Flask_DataTables_peewee-0.1.2.dist-info/LICENSE
Flask_DataTables_peewee-0.1.2.dist-info/METADATA
Flask_DataTables_peewee-0.1.2.dist-info/WHEEL
Flask_DataTables_peewee-0.1.2.dist-info/top_level.txt
Flask_DataTables_peewee-0.1.2.dist-info/RECORD
