Metadata-Version: 2.1
Name: Flask-DataTables-peewee
Version: 0.1.2
Summary: Flask integration with DataTables and peewee.
Home-page: https://github.com/tekidltd/Flask-DataTables
Author: TEKID Ltd.
Author-email: contact@tek-id.com
Maintainer: Jarry XIAO
Maintainer-email: jarry.xiao@tek-id.com
License: BSD 3-Clause License
Download-URL: https://github.com/tekidltd/Flask-DataTables/archive/v0.1.2.tar.gz
Keywords: flask,peewee,datatables
Platform: any
Classifier: Development Status :: 5 - Production/Stable
Classifier: Intended Audience :: Developers
Classifier: License :: OSI Approved :: BSD License
Classifier: Natural Language :: English
Classifier: Operating System :: OS Independent
Classifier: Programming Language :: Python
Classifier: Programming Language :: Python :: 3.6
Classifier: Programming Language :: Python :: 3.7
Classifier: Programming Language :: Python :: 3.8
Classifier: Programming Language :: Python :: 3.9
Classifier: Programming Language :: Python :: 3 :: Only
Classifier: Topic :: Software Development
Classifier: Topic :: Utilities
Classifier: Typing :: Typed
Requires-Python: >=3.6
Requires-Dist: Flask
Requires-Dist: peewee
Requires-Dist: typing-extensions
Requires-Dist: typing ; python_version < "3.5"
